study.py
study_cli-0.0.1.dist-info/LICENSE
study_cli-0.0.1.dist-info/METADATA
study_cli-0.0.1.dist-info/WHEEL
study_cli-0.0.1.dist-info/entry_points.txt
study_cli-0.0.1.dist-info/top_level.txt
study_cli-0.0.1.dist-info/RECORD
