Metadata-Version: 2.1
Name: study-cli
Version: 0.0.1
Summary: command line flash cards
Home-page: https://github.com/fawzisal/study-cli
Author: Fawzi Sal
Author-email: Example Author <fawzisal001@gmail.com>
License: GPLv3
Project-URL: Homepage, https://github.com/fawzisal/study-cli
Project-URL: Bug Tracker, https://github.com/fawzisal/study-cli/issues
Platform: any
Classifier: Programming Language :: Python :: 3
Classifier: License :: OSI Approved :: MIT License
Classifier: Operating System :: OS Independent
Requires-Python: >=3.6
License-File: LICENSE
